README.md
setup.py
Topsis_102116022.egg-info/PKG-INFO
Topsis_102116022.egg-info/SOURCES.txt
Topsis_102116022.egg-info/dependency_links.txt
Topsis_102116022.egg-info/entry_points.txt
Topsis_102116022.egg-info/requires.txt
Topsis_102116022.egg-info/top_level.txt
Topsis_Kunal_102116022/topsis.py