Metadata-Version: 2.1
Name: Topsis-102116022
Version: 1.0.0
Summary: Calculates Topsis Score and Rank
Home-page: https://github.com/kunalarora0930/Topsis_Kunal_102116022
Author: Kunal Arora
Author-email: arorakunal0930@gmail.com
License: MIT
Platform: UNKNOWN
Classifier: Programming Language :: Python :: 3
Classifier: License :: OSI Approved :: MIT License
Classifier: Operating System :: OS Independent
